{
  "project_info": {
    "project_number": "586934695423",
    "project_id": "compozanet-activator",
    "storage_bucket": "compozanet-activator.appspot.com"
  },
  "client": [
    {
      "client_info": {
        "mobilesdk_app_id": "1:586934695423:android:629534d0ded0b7edebe3ca",
        "android_client_info": {
          "package_name": "net.compoza.activator"
        }
      },
      "oauth_client": [
        {
          "client_id": "586934695423-9vc4qte5c3itordve0rfef7hn1d3d48q.apps.googleusercontent.com",
          "client_type": 1,
          "android_info": {
            "package_name": "net.compoza.activator",
            "certificate_hash": "40e85253374a4541a65931fb4fa433e8554ef98e"
          }
        },
        {
          "client_id": "586934695423-p1h5mappurtfp45p3lll6lqnir75808r.apps.googleusercontent.com",
          "client_type": 1,
          "android_info": {
            "package_name": "net.compoza.activator",
            "certificate_hash": "c91e2f8eef6da2860d2384fab8376dba3bb8ca7b"
          }
        },
        {
          "client_id": "586934695423-rkg8qihjdvo8mu16ukaeg9sr4p6piedn.apps.googleusercontent.com",
          "client_type": 1,
          "android_info": {
            "package_name": "net.compoza.activator",
            "certificate_hash": "276cac5180ae5555299092a3bec29e8b2ed8ec1d"
          }
        },
        {
          "client_id": "586934695423-s6s4quarvm5vg6bfps2sss1fr5ngobt2.apps.googleusercontent.com",
          "client_type": 1,
          "android_info": {
            "package_name": "net.compoza.activator",
            "certificate_hash": "9ce7664979bd135b069e724036666c0d986b74a0"
          }
        },
        {
          "client_id": "586934695423-ljcgidmaadaje4v95g923o6ppd9r65tc.apps.googleusercontent.com",
          "client_type": 3
        }
      ],
      "api_key": [
        {
          "current_key": "AIzaSyDBTM367A4QynW8WsbBrcR-Dxu2UnS7hy4"
        }
      ],
      "services": {
        "appinvite_service": {
          "other_platform_oauth_client": [
            {
              "client_id": "586934695423-ljcgidmaadaje4v95g923o6ppd9r65tc.apps.googleusercontent.com",
              "client_type": 3
            },
            {
              "client_id": "586934695423-vl249okhrk8kfr5efeb5i9510umua7oi.apps.googleusercontent.com",
              "client_type": 2,
              "ios_info": {
                "bundle_id": "net.compoza.activator"
              }
            }
          ]
        }
      }
    }
  ],
  "configuration_version": "1"
}